beefly/__init__.py
beefly-0.8.0.dist-info/METADATA
beefly-0.8.0.dist-info/RECORD
beefly-0.8.0.dist-info/WHEEL
beefly-0.8.0.dist-info/top_level.txt
