Metadata-Version: 2.1
Name: beefly
Version: 0.8.0
Summary: Dynamic visualization training service in Jupyter Notebook for Keras tf.keras and others.
Home-page: https://github.com/Hourout/beefly
Author: JinQing Lee, Gaojie Wei
Author-email: hourout@163.com
License: Apache License Version 2.0
Keywords: keras-visualization,keras,tf.keras,plot,chart
Platform: UNKNOWN
Classifier: Framework :: Jupyter
Classifier: Intended Audience :: Developers
Classifier: Intended Audience :: Education
Classifier: Intended Audience :: Science/Research
Classifier: License :: OSI Approved :: Apache Software License
Classifier: Topic :: Scientific/Engineering
Classifier: Topic :: Scientific/Engineering :: Artificial Intelligence
Classifier: Topic :: Scientific/Engineering :: Visualization
Classifier: Programming Language :: Python :: 3.5
Classifier: Programming Language :: Python :: 3.6
Requires-Dist: tensorview (>=0.3.0)
